<?xml version="1.0" encoding="utf-16"?>
<Ac4yAssociation xmlns:xsi="http://www.w3.org/2001/XMLSchema-instance" xmlns:xsd="http://www.w3.org/2001/XMLSchema">
  <Id>789</Id>
  <GUID>0509B1A5-2B00-4BF6-81E6-9593F48D6BE1</GUID>
  <OriginId>20</OriginId>
  <OriginGUID>22802AAA-C3A2-457C-9F56-2F08E569D993</OriginGUID>
  <OriginHumanId>Tor_Bankszamla_Kezeles</OriginHumanId>
  <OriginPublicHumanId>Tor_Bankszamla_Kezeles</OriginPublicHumanId>
  <OriginSimpledHumanId>TORBANKSZAMLAKEZELES</OriginSimpledHumanId>
  <OriginNamespace />
  <OriginTemplateId>19</OriginTemplateId>
  <OriginTemplateGUID>40657D3E-0553-41DB-ACE1-B0B4F9432B77</OriginTemplateGUID>
  <OriginTemplateHumanId>tárolt eljárás</OriginTemplateHumanId>
  <OriginTemplatePublicHumanId>tárolt eljárás</OriginTemplatePublicHumanId>
  <OriginTemplateSimpledHumanId>TAROLTELJARAS</OriginTemplateSimpledHumanId>
  <OriginTemplateNamespace />
  <TargetId>1226</TargetId>
  <TargetGUID>DFC254F6-4637-49AA-9921-DFD8A9220C4A</TargetGUID>
  <TargetHumanId>Tor_Bankszamla_Kezeles.Új bankszámla rögzítése</TargetHumanId>
  <TargetPublicHumanId>Új bankszámla rögzítése</TargetPublicHumanId>
  <TargetSimpledHumanId>TORBANKSZAMLAKEZELES.UJBANKSZAMLAROGZITESE</TargetSimpledHumanId>
  <TargetNamespace />
  <TargetTemplateId>1058</TargetTemplateId>
  <TargetTemplateGUID>70F207BD-085C-4FA1-BCA1-D32515E01062</TargetTemplateGUID>
  <TargetTemplateHumanId>Metódus</TargetTemplateHumanId>
  <TargetTemplatePublicHumanId>Metódus</TargetTemplatePublicHumanId>
  <TargetTemplateSimpledHumanId>METODUS</TargetTemplateSimpledHumanId>
  <TargetTemplateNamespace />
  <AssociationPathId>1060</AssociationPathId>
  <AssociationPathGUID>F0ABAA98-B0C2-42E1-90F5-D5E4FEEF04E7</AssociationPathGUID>
  <AssociationPathHumanId>Tárolt eljárás.metódus</AssociationPathHumanId>
  <AssociationPathPublicHumanId>metódus</AssociationPathPublicHumanId>
  <AssociationPathSimpledHumanId>TAROLTELJARAS.METODUS</AssociationPathSimpledHumanId>
  <AssociationPathNamespace />
  <ActualityId>0</ActualityId>
  <OrderNumber>4</OrderNumber>
</Ac4yAssociation>