<?xml version="1.0" encoding="utf-16"?>
<Ac4yAssociation xmlns:xsi="http://www.w3.org/2001/XMLSchema-instance" xmlns:xsd="http://www.w3.org/2001/XMLSchema">
  <Id>313</Id>
  <GUID>9412833F-2FBD-407F-9EC9-6FFAC48B6076</GUID>
  <OriginId>82</OriginId>
  <OriginGUID>BA5DE6C7-7B13-4FE6-A65A-69F8616C4FC4</OriginGUID>
  <OriginHumanId>tblUgynokSzerzodes</OriginHumanId>
  <OriginPublicHumanId>tblUgynokSzerzodes</OriginPublicHumanId>
  <OriginSimpledHumanId>TBLUGYNOKSZERZODES</OriginSimpledHumanId>
  <OriginNamespace />
  <OriginTemplateId>59</OriginTemplateId>
  <OriginTemplateGUID>D95EAD10-79AA-47F0-AF87-C546BF9CF664</OriginTemplateGUID>
  <OriginTemplateHumanId>Tábla</OriginTemplateHumanId>
  <OriginTemplatePublicHumanId>Tábla</OriginTemplatePublicHumanId>
  <OriginTemplateSimpledHumanId>TABLA</OriginTemplateSimpledHumanId>
  <OriginTemplateNamespace />
  <TargetId>380</TargetId>
  <TargetGUID>47AA13A7-5DB1-420C-963D-1FB77E880CE7</TargetGUID>
  <TargetHumanId>UgySzerForJut3</TargetHumanId>
  <TargetPublicHumanId>UgySzerForJut3</TargetPublicHumanId>
  <TargetSimpledHumanId>UGYSZERFORJUT3</TargetSimpledHumanId>
  <TargetNamespace />
  <TargetTemplateId>184</TargetTemplateId>
  <TargetTemplateGUID>F08E0A74-0F89-48A2-BA8A-1D98BE49CF84</TargetTemplateGUID>
  <TargetTemplateHumanId>tábla oszlop</TargetTemplateHumanId>
  <TargetTemplatePublicHumanId>tábla oszlop</TargetTemplatePublicHumanId>
  <TargetTemplateSimpledHumanId>TABLAOSZLOP</TargetTemplateSimpledHumanId>
  <TargetTemplateNamespace />
  <AssociationPathId>186</AssociationPathId>
  <AssociationPathGUID>5E944A6E-76A0-4EC2-AD13-211435863B8F</AssociationPathGUID>
  <AssociationPathHumanId>tábla.oszlop</AssociationPathHumanId>
  <AssociationPathPublicHumanId>oszlop</AssociationPathPublicHumanId>
  <AssociationPathSimpledHumanId>TABLA.OSZLOP</AssociationPathSimpledHumanId>
  <AssociationPathNamespace />
  <ActualityId>0</ActualityId>
  <OrderNumber>0</OrderNumber>
</Ac4yAssociation>